README.rst
chronos.py
setup.cfg
setup.py
chronospy.egg-info/PKG-INFO
chronospy.egg-info/SOURCES.txt
chronospy.egg-info/dependency_links.txt
chronospy.egg-info/requires.txt
chronospy.egg-info/top_level.txt