Metadata-Version: 1.1
Name: chronospy
Version: 0.1.1
Summary: Mutil-thread/mutil-process task scheduler drive by Tornado IOLoop for human.
Home-page: UNKNOWN
Author: Thomas Huang
Author-email: lyanghwy@gmail.com
License: GPL
Keywords: schedule,periodic,jobs,scheduling,clockwork,cron
Platform: any
Classifier: Development Status :: 3 - Alpha
Classifier: License :: OSI Approved :: GNU Affero General Public License v3
Classifier: Natural Language :: English
Classifier: Programming Language :: Python
Classifier: Programming Language :: Python :: 2.7
Classifier: Operating System :: OS Independent
